tystrings/__init__.py
tystrings/baidu.py
tystrings/cli.py
tystrings/strings.py
tystrings/translator.py
tystrings/tyformatter.py
tystrings/tylogger.py
tystrings/version.py
tystrings-1.2.3.dist-info/LICENSE
tystrings-1.2.3.dist-info/METADATA
tystrings-1.2.3.dist-info/WHEEL
tystrings-1.2.3.dist-info/entry_points.txt
tystrings-1.2.3.dist-info/top_level.txt
tystrings-1.2.3.dist-info/RECORD
