Metadata-Version: 2.1
Name: tystrings
Version: 1.2.3
Summary: strings file tool for iOS / macOS developers
Home-page: https://github.com/luckytianyiyan/TyStrings
Author: luckytianyiyan
Author-email: luckytianyiyan@gmail.com
License: MIT
Keywords: i18n,iOS,localization,internationalization,strings,.strings
Platform: UNKNOWN
Classifier: Development Status :: 5 - Production/Stable
Classifier: Intended Audience :: Developers
Classifier: Topic :: Software Development :: Internationalization
Classifier: Topic :: Software Development :: Interpreters
Classifier: License :: OSI Approved :: MIT License
Classifier: Programming Language :: Python :: 3
Classifier: Operating System :: MacOS :: MacOS X
Requires-Dist: colorama (>=0.4.3)
Requires-Dist: requests (>=2.24.0)
Requires-Dist: tabulate (>=0.8.7)
